odoo/addons/ssi_cost_accounting/README.rst
odoo/addons/ssi_cost_accounting/__init__.py
odoo/addons/ssi_cost_accounting/__manifest__.py
odoo/addons/ssi_cost_accounting/menu.xml
odoo/addons/ssi_cost_accounting/models/__init__.py
odoo/addons/ssi_cost_accounting/models/account_account.py
odoo/addons/ssi_cost_accounting/models/account_analytic_account.py
odoo/addons/ssi_cost_accounting/models/account_analytic_group.py
odoo/addons/ssi_cost_accounting/models/account_move.py
odoo/addons/ssi_cost_accounting/models/account_move_line.py
odoo/addons/ssi_cost_accounting/models/mixin_analytic_account_m2o_configurator.py
odoo/addons/ssi_cost_accounting/models/mixin_analytic_group_m2o_configurator.py
odoo/addons/ssi_cost_accounting/models/res_company.py
odoo/addons/ssi_cost_accounting/models/res_config_settings.py
odoo/addons/ssi_cost_accounting/security/ir_module_category_data.xml
odoo/addons/ssi_cost_accounting/security/res_group_data.xml
odoo/addons/ssi_cost_accounting/static/description/icon.png
odoo/addons/ssi_cost_accounting/templates/analytic_account_m2o_configurator_templates.xml
odoo/addons/ssi_cost_accounting/templates/analytic_group_m2o_configurator_templates.xml
odoo/addons/ssi_cost_accounting/views/account_account_views.xml
odoo/addons/ssi_cost_accounting/views/account_analytic_account_views.xml
odoo/addons/ssi_cost_accounting/views/account_analytic_group_views.xml
odoo/addons/ssi_cost_accounting/views/account_analytic_tag_views.xml
odoo/addons/ssi_cost_accounting/views/res_config_settings_views.xml
odoo14_addon_ssi_cost_accounting-14.0.2.3.0.dist-info/METADATA
odoo14_addon_ssi_cost_accounting-14.0.2.3.0.dist-info/WHEEL
odoo14_addon_ssi_cost_accounting-14.0.2.3.0.dist-info/top_level.txt
odoo14_addon_ssi_cost_accounting-14.0.2.3.0.dist-info/RECORD
